topsis_101883071/__init__.py
topsis_101883071/topsis_101883071.py
topsis_101883071-2.0.0.dist-info/LICENSE
topsis_101883071-2.0.0.dist-info/METADATA
topsis_101883071-2.0.0.dist-info/WHEEL
topsis_101883071-2.0.0.dist-info/entry_points.txt
topsis_101883071-2.0.0.dist-info/top_level.txt
topsis_101883071-2.0.0.dist-info/RECORD
