Metadata-Version: 2.1
Name: topsis-101883071
Version: 2.0.0
Summary: Python package to implement TOPSIS
Home-page: https://github.com/
Author: Yogesh
Author-email: ysingla001@gmail.com
License: MIT
Platform: UNKNOWN
Classifier: License :: OSI Approved :: MIT License
Classifier: Programming Language :: Python :: 3
Classifier: Programming Language :: Python :: 3.7
